drf_link_header_pagination/__init__.py
drf_link_header_pagination-0.2.0.dist-info/LICENSE
drf_link_header_pagination-0.2.0.dist-info/METADATA
drf_link_header_pagination-0.2.0.dist-info/WHEEL
drf_link_header_pagination-0.2.0.dist-info/top_level.txt
drf_link_header_pagination-0.2.0.dist-info/RECORD
