Metadata-Version: 2.1
Name: drf-link-header-pagination
Version: 0.2.0
Summary: Link Header Pagination for Django Rest Framework
License: BSD 3-Clause License
Classifier: Framework :: Django
Classifier: Programming Language :: Python :: 3
Classifier: Intended Audience :: Developers
Classifier: Operating System :: OS Independent
Classifier: Natural Language :: English
Classifier: Topic :: Internet :: WWW/HTTP
Requires-Python: >=3.6
License-File: LICENSE
Requires-Dist: djangorestframework (>=3.11)
